catcher/__init__.py
catcher/__main__.py
catcher/core/__init__.py
catcher/core/filters_factory.py
catcher/core/include.py
catcher/core/mod_factory.py
catcher/core/parser.py
catcher/core/runner.py
catcher/core/step_factory.py
catcher/core/test.py
catcher/core/var_holder.py
catcher/modules/__init__.py
catcher/modules/compose.py
catcher/modules/formatter.py
catcher/modules/log_storage.py
catcher/modules/requirements.py
catcher/modules/filter_impl/__init__.py
catcher/modules/filter_impl/bifs.py
catcher/resources/__init__.py
catcher/resources/custom_expand.js
catcher/resources/default.css
catcher/resources/index.html
catcher/resources/jquery.expander.min.js
catcher/resources/jquery.js
catcher/resources/logo_small.png
catcher/resources/raw.log.html
catcher/resources/system.log.html
catcher/resources/test.log.html
catcher/resources/yml_display.html
catcher/steps/__init__.py
catcher/steps/check.py
catcher/steps/echo.py
catcher/steps/external.py
catcher/steps/external_step.py
catcher/steps/grpc_step.py
catcher/steps/http.py
catcher/steps/loop.py
catcher/steps/run.py
catcher/steps/sh_step.py
catcher/steps/step.py
catcher/steps/stop.py
catcher/steps/wait.py
catcher/utils/__init__.py
catcher/utils/external_utils.py
catcher/utils/file_utils.py
catcher/utils/internal_utils.py
catcher/utils/logger.py
catcher/utils/misc.py
catcher/utils/module_utils.py
catcher/utils/singleton.py
catcher/utils/time_utils.py
test/__init__.py
test/abs_test_class.py
test/test_utils.py
test/core/__init__.py
test/core/e2e_test.py
test/core/filters_test.py
test/core/finally_test.py
test/core/inventory_test.py
test/core/output_test.py
test/core/run_test.py
test/core/variables_test.py
test/includes/__init__.py
test/includes/include_files_test.py
test/includes/run_registered_test.py
test/includes/variables_includes_test.py
test/modules/__init__.py
test/modules/compose_test.py
test/resources/__init__.py
test/resources/calculator.py
test/resources/greeter.py
test/steps/__init__.py
test/steps/checks_test.py
catcher-1.36.3.dist-info/LICENSE
catcher-1.36.3.dist-info/METADATA
catcher-1.36.3.dist-info/WHEEL
catcher-1.36.3.dist-info/entry_points.txt
catcher-1.36.3.dist-info/top_level.txt
catcher-1.36.3.dist-info/RECORD
