Metadata-Version: 2.1
Name: catcher
Version: 1.36.3
Summary: Microservices automated test tool.
Home-page: https://github.com/comtihon/catcher
Author: Valerii Tikhonov, Ekaterina Belova
Author-email: valerii.tikhonov@gmail.com
Classifier: Intended Audience :: Developers
Classifier: License :: OSI Approved :: Apache Software License
Classifier: Programming Language :: Python :: 3.8
Classifier: Programming Language :: Python :: 3.9
Classifier: Programming Language :: Python :: 3.10
Classifier: Topic :: Software Development :: Testing
License-File: LICENSE
Requires-Dist: docopt (==0.6.2)
Requires-Dist: mock (==5.0.2)
Requires-Dist: pytest (==7.4.0)
Requires-Dist: requests (==2.31.0)
Requires-Dist: urllib3 (==2.0.3)
Requires-Dist: requests-mock (==1.11.0)
Requires-Dist: PyYAML (==6.0)
Requires-Dist: Jinja2 (==3.1.2)
Requires-Dist: Faker (==18.11.1)
Requires-Dist: colorama (==0.4.6)
Requires-Dist: networkx (==3.1)
Requires-Dist: grpcio (==1.56.0)
Requires-Dist: grpcio-tools (==1.56.0)
